telegram_sleuth_naufalmng/__init__.py
telegram_sleuth_naufalmng/example.py
telegram_group_sleuth-0.0.1.dist-info/LICENSE
telegram_group_sleuth-0.0.1.dist-info/METADATA
telegram_group_sleuth-0.0.1.dist-info/WHEEL
telegram_group_sleuth-0.0.1.dist-info/top_level.txt
telegram_group_sleuth-0.0.1.dist-info/RECORD
