Metadata-Version: 2.1
Name: telegram_group_sleuth
Version: 0.0.1
Summary: Extract and analyze data from Telegram group chats
Author-email: Naufal Hanif <naufalmng@gmail.com>
Project-URL: Homepage, https://github.com/naufalmng/telegram-group-sleuth
Project-URL: Issues, https://github.com/naufalmng/telegram-group-sleuth/issues
Classifier: Programming Language :: Python :: 3
Classifier: License :: OSI Approved :: GNU General Public License v3 (GPLv3)
Classifier: Operating System :: OS Independent
Requires-Python: >=3.8
License-File: LICENSE
